topsis/102003578.py
topsis/__init__.py
topsis_102003578-1.0.0.1.dist-info/METADATA
topsis_102003578-1.0.0.1.dist-info/WHEEL
topsis_102003578-1.0.0.1.dist-info/licenses/LICENSE.txt
topsis_102003578-1.0.0.1.dist-info/RECORD
